signal_slot/__init__.py
signal_slot/queue_utils.py
signal_slot/signal_slot.py
signal_slot/utils.py
tests/__init__.py
tests/test_signal_slot.py
signal_slot_mp-1.0.5.dist-info/LICENSE
signal_slot_mp-1.0.5.dist-info/METADATA
signal_slot_mp-1.0.5.dist-info/WHEEL
signal_slot_mp-1.0.5.dist-info/top_level.txt
signal_slot_mp-1.0.5.dist-info/RECORD
