Metadata-Version: 2.1
Name: signal-slot-mp
Version: 1.0.5
Summary: Fast and compact framework for communication between threads and processes in Python using event loops, signals and slots.
Home-page: https://github.com/alex-petrenko/signal-slot
Author: Aleksei Petrenko
License: MIT
Project-URL: Github, https://github.com/alex-petrenko/signal-slot
Project-URL: Sample Factory, https://github.com/alex-petrenko/sample-factory
Keywords: asynchronous multithreading multiprocessing queue faster-fifo signal slot event loop
Requires-Python: >=3.8
License-File: LICENSE
Requires-Dist: faster-fifo (<2.0,>=1.4.4)
Provides-Extra: dev
Requires-Dist: black ; extra == 'dev'
Requires-Dist: isort ; extra == 'dev'
Requires-Dist: pytest (<8.0) ; extra == 'dev'
Requires-Dist: flake8 ; extra == 'dev'
Requires-Dist: pre-commit ; extra == 'dev'
Requires-Dist: twine ; extra == 'dev'
